[
  {
    "id": "arthur-conan-d74e57bab7",
    "quote": "Quando você elimina o impossível, o que sobra, por mais improvável que pareça, só pode ser a verdade.",
    "author": "Arthur Conan Doyle",
    "lang": "pt",
    "tags": [],
    "source": "local"
  },
  {
    "id": "arist-teles-448822174c",
    "quote": "A dúvida é o principio da sabedoria.",
    "author": "Aristóteles",
    "lang": "pt",
    "tags": [],
    "source": "local"
  },
  {
    "id": "arist-teles-d01987ef91",
    "quote": "A grandeza não consiste em receber honras, mas em merecê-las",
    "author": "Aristóteles",
    "lang": "pt",
    "tags": [],
    "source": "local"
  },
  {
    "id": "blaise-pasca-346085b797",
    "quote": "O coração tem razões que a própria razão desconhece.",
    "author": "Blaise Pascal",
    "lang": "pt",
    "tags": [],
    "source": "local"
  },
  {
    "id": "steve-jobs-16f462a0b9",
    "quote": "Você pode encarar o erro como uma besteira a ser esquecida, ou como um resultado que aponta uma nova direção",
    "author": "Steve Jobs",
    "lang": "pt",
    "tags": [],
    "source": "local"
  },
  {
    "id": "steve-jobs-49b99f619b",
    "quote": "Tenha coragem de seguir o que seu coração e sua intuição dizem. Eles já sabem o que você realmente deseja. Todo o resto é secundário",
    "author": "Steve Jobs",
    "lang": "pt",
    "tags": [],
    "source": "local"
  },
  {
    "id": "steve-jobs-3b7219fdf9",
    "quote": "A única maneira de fazer um bom trabalho é amando o que você faz. Se você ainda não encontrou, continue procurando. Não se desespere. Assim como no amor, você saberá quando tiver encontrado.",
    "author": "Steve Jobs",
    "lang": "pt",
    "tags": [],
    "source": "local"
  },
  {
    "id": "steve-jobs-ec6bf42917",
    "quote": "Não deixe que o ruído da opinião alheia impeça que você escute a sua voz interior.",
    "author": "Steve Jobs",
    "lang": "pt",
    "tags": [],
    "source": "local"
  },
  {
    "id": "richard-rest-8f42189f4b",
    "quote": "Aprenda a parar de desperdiçar energia mental com coisas que estão além do seu controle",
    "author": "Richard Restak",
    "lang": "pt",
    "tags": [],
    "source": "local"
  },
  {
    "id": "charles-chap-c988f0f4e2",
    "quote": "A persistência é o menor caminho do êxito",
    "author": "Charles Chaplin",
    "lang": "pt",
    "tags": [],
    "source": "local"
  },
  {
    "id": "mark-twain-94c51c407e",
    "quote": "Coragem é a resistência ao medo, domínio do medo, e não a ausência do medo.",
    "author": "Mark Twain",
    "lang": "pt",
    "tags": [],
    "source": "local"
  },
  {
    "id": "jesus-de-naz-7a7da5ea19",
    "quote": "Por isso, não fiquem preocupados com o dia de amanhã, pois o dia de amanhã trará as suas próprias preocupações. Para cada dia bastam as suas próprias dificuldades.",
    "author": "Jesus de Nazaré",
    "lang": "pt",
    "tags": [],
    "source": "local"
  },
  {
    "id": "mahatma-gand-05eed23bb3",
    "quote": "A alegria está na luta, na tentativa, no sofrimento envolvido. Não na vitória propriamente dita",
    "author": "Mahatma Gandhi",
    "lang": "pt",
    "tags": [],
    "source": "local"
  },
  {
    "id": "mahatma-gand-b3e81caef0",
    "quote": "Não existe um caminho para a felicidade. A felicidade é o caminho.",
    "author": "Mahatma Gandhi",
    "lang": "pt",
    "tags": [],
    "source": "local"
  },
  {
    "id": "mahatma-gand-5483d9f5a5",
    "quote": "Você deve ser a mudança que deseja ver no mundo.",
    "author": "Mahatma Gandhi",
    "lang": "pt",
    "tags": [],
    "source": "local"
  },
  {
    "id": "david-allen-59b6ee684b",
    "quote": "Você pode fazer qualquer coisa, mas não tudo.",
    "author": "David Allen",
    "lang": "pt",
    "tags": [],
    "source": "local"
  },
  {
    "id": "albert-einst-5a90a46c7e",
    "quote": "A imaginação é mais importante que a ciência, porque a ciência é limitada, ao passo que a imaginação abrange o mundo inteiro.",
    "author": "Albert Einstein",
    "lang": "pt",
    "tags": [],
    "source": "local"
  },
  {
    "id": "albert-einst-b111011b7c",
    "quote": "A felicidade não se resume na ausência de problemas, mas sim na sua capacidade de lidar com eles.",
    "author": "Albert Einstein",
    "lang": "pt",
    "tags": [],
    "source": "local"
  },
  {
    "id": "albert-einst-a2bde922a8",
    "quote": "O impossível existe até que alguém duvide dele e prove o contrário.",
    "author": "Albert Einstein",
    "lang": "pt",
    "tags": [],
    "source": "local"
  },
  {
    "id": "bob-marley-2502c17094",
    "quote": "Enquanto a cor da pele for mais importante que o brilho dos olhos, haverá guerra.",
    "author": "Bob Marley",
    "lang": "pt",
    "tags": [],
    "source": "local"
  },
  {
    "id": "amelia-earha-b973a1766b",
    "quote": "A coisa mais difícil é a decisão de agir, o resto é apenas tenacidade.",
    "author": "Amelia Earhart",
    "lang": "pt",
    "tags": [],
    "source": "local"
  },
  {
    "id": "john-lennon-f11dbb711a",
    "quote": "A vida é aquilo que acontece enquanto você está fazendo outros planos.",
    "author": "John Lennon",
    "lang": "pt",
    "tags": [],
    "source": "local"
  },
  {
    "id": "buddha-246f0c4a77",
    "quote": "A Mente É Tudo. O Que Você Pensa, Você Se Torna.",
    "author": "Buddha",
    "lang": "pt",
    "tags": [],
    "source": "local"
  },
  {
    "id": "jk-rowling-e9bdf46e94",
    "quote": "Pode se encontrar a felicidade mesmo nas horas mais sombrias, se a pessoa se lembrar de acender a luz.",
    "author": "JK Rowling",
    "lang": "pt",
    "tags": [],
    "source": "local"
  },
  {
    "id": "suzanne-coll-2624673e82",
    "quote": "Esperança é a única coisa mais forte que o medo. Um pouco de esperança é eficaz, muita esperança é perigoso. Faíscas são boas enquanto são contidas.",
    "author": "Suzanne Collins",
    "lang": "pt",
    "tags": [],
    "source": "local"
  },
  {
    "id": "antoine-de-s-40a5ee1f61",
    "quote": "Tu te tornas eternamente responsável por aquilo que cativas.",
    "author": "Antoine de Saint-Exupéry",
    "lang": "pt",
    "tags": [],
    "source": "local"
  },
  {
    "id": "s-o-francisc-ae4ce349c1",
    "quote": "Comece fazendo o que é necessário, depois o que é possível, e de repente você estará fazendo o impossível.",
    "author": "São Francisco de Assis",
    "lang": "pt",
    "tags": [],
    "source": "local"
  },
  {
    "id": "theodore-roo-b34eddd655",
    "quote": "Acredite que você pode, assim você já está no meio do caminho.",
    "author": "Theodore Roosevelt",
    "lang": "pt",
    "tags": [],
    "source": "local"
  },
  {
    "id": "conf-cio-8d138968d0",
    "quote": "Não importa o quanto você vá devagar desde que não pare",
    "author": "Confúcio",
    "lang": "pt",
    "tags": [],
    "source": "local"
  },
  {
    "id": "thomas-a-edi-be45e8731c",
    "quote": "Nossa maior fraqueza está em desistir. O caminho mais certo de vencer é tentar mais uma vez.",
    "author": "Thomas A. Edison",
    "lang": "pt",
    "tags": [],
    "source": "local"
  },
  {
    "id": "conf-cio-bb2825059f",
    "quote": "A vontade de vencer, o desejo de sucesso, o desejo de atingir seu pleno potencial. Estas são as chaves que irão abrir a porta para a excelência pessoal",
    "author": "Confúcio",
    "lang": "pt",
    "tags": [],
    "source": "local"
  },
  {
    "id": "sam-levenson-808bcb9519",
    "quote": "Não olhe para o relógio. Faça o que ele faz: continue se movendo.",
    "author": "Sam Levenson",
    "lang": "pt",
    "tags": [],
    "source": "local"
  },
  {
    "id": "ayn-rand-def89f3492",
    "quote": "Um homem criativo é motivado pelo desejo de realizar, não pelo desejo de vencer os outros.",
    "author": "Ayn Rand",
    "lang": "pt",
    "tags": [],
    "source": "local"
  },
  {
    "id": "samuel-becke-0e9d338d2e",
    "quote": "Tente de novo, falhe novamente. Falhe melhor.",
    "author": "Samuel Beckett",
    "lang": "pt",
    "tags": [],
    "source": "local"
  },
  {
    "id": "oscar-wilde-daed8d7c6b",
    "quote": "Seja você mesmo, porque todos os outros já existem.",
    "author": "Oscar Wilde",
    "lang": "pt",
    "tags": [],
    "source": "local"
  },
  {
    "id": "albert-einst-4a30fb8ec1",
    "quote": "Duas coisas são infinitas: o universo e a estupidez humana. Mas, em relação ao universo, ainda não tenho certeza absoluta.",
    "author": "Albert Einstein",
    "lang": "pt",
    "tags": [],
    "source": "local"
  },
  {
    "id": "jim-wright-edbf7144f0",
    "quote": "Lembre-se sempre que você é absolutamente único. Assim como todos os outros.",
    "author": "Jim Wright",
    "lang": "pt",
    "tags": [],
    "source": "local"
  },
  {
    "id": "isaac-asimov-486a799017",
    "quote": "As pessoas que pensam que sabem tudo são um grande aborrecimento para aqueles de nós que sabem.",
    "author": "Isaac Asimov",
    "lang": "pt",
    "tags": [],
    "source": "local"
  },
  {
    "id": "dalai-lama-bea2f2fadf",
    "quote": "A felicidade não é algo pronto. Ela é feita das suas próprias ações.",
    "author": "Dalai Lama",
    "lang": "pt",
    "tags": [],
    "source": "local"
  },
  {
    "id": "albert-einst-f0e8997121",
    "quote": "O mundo não está ameaçado pelas pessoas más, e sim por aquelas que permitem a maldade.",
    "author": "Albert Einstein",
    "lang": "pt",
    "tags": [],
    "source": "local"
  },
  {
    "id": "albert-einst-6086949005",
    "quote": "Quem nunca errou nunca experimentou nada novo.",
    "author": "Albert Einstein",
    "lang": "pt",
    "tags": [],
    "source": "local"
  },
  {
    "id": "albert-einst-48b977f5cf",
    "quote": "O primeiro dever da inteligência é desconfiar dela mesma.",
    "author": "Albert Einstein",
    "lang": "pt",
    "tags": [],
    "source": "local"
  },
  {
    "id": "albert-einst-9176366fcd",
    "quote": "A percepção do desconhecido é a mais fascinante das experiências. O homem que não tem os olhos abertos para o misterioso passará pela vida sem ver nada.",
    "author": "Albert Einstein",
    "lang": "pt",
    "tags": [],
    "source": "local"
  },
  {
    "id": "albert-einst-151d02dd37",
    "quote": "A mais bela coisa que podemos vivenciar é o mistério. Ele é fonte de qualquer arte verdadeira e qualquer ciência. Aquele que desconhece esta emoção, aquele que não para mais para pensar e não se fascina, está como morto: seus olhos estão fechados.",
    "author": "Albert Einstein",
    "lang": "pt",
    "tags": [],
    "source": "local"
  },
  {
    "id": "albert-einst-2150aba9cf",
    "quote": "Há duas formas para viver a sua vida. Uma é acreditar que não existe milagre. A outra é acreditar que todas as coisas são um milagre.",
    "author": "Albert Einstein",
    "lang": "pt",
    "tags": [],
    "source": "local"
  },
  {
    "id": "albert-einst-8b75c3ed72",
    "quote": "A alegria de ver e entender é o mais perfeito dom da natureza.",
    "author": "Albert Einstein",
    "lang": "pt",
    "tags": [],
    "source": "local"
  },
  {
    "id": "albert-einst-345e8bdfdf",
    "quote": "Não se deve ir atrás de objetivos fáceis, é preciso buscar o que só pode ser alcançado por meio dos maiores esforços.",
    "author": "Albert Einstein",
    "lang": "pt",
    "tags": [],
    "source": "local"
  },
  {
    "id": "albert-einst-b111011b7c",
    "quote": "A felicidade não se resume na ausência de problemas, mas sim na sua capacidade de lidar com eles.",
    "author": "Albert Einstein",
    "lang": "pt",
    "tags": [],
    "source": "local"
  },
  {
    "id": "neil-degrass-28abe3b608",
    "quote": "Tudo bem não saber todas as respostas. É melhor admitir ignorância do que acreditar  em verdades que são falsas. Fingir saber de tudo fecha as portas para que a gente enxergue a realidade da forma como ela é.",
    "author": "Neil deGrasse Tyson",
    "lang": "pt",
    "tags": [],
    "source": "local"
  },
  {
    "id": "neil-degrass-27de97c321",
    "quote": "As pessoas mais criativas são motivadas pelos maiores dos problemas que se apresentam diante delas.",
    "author": "Neil deGrasse Tyson",
    "lang": "pt",
    "tags": [],
    "source": "local"
  },
  {
    "id": "neil-degrass-7a7e39637b",
    "quote": "Uma coisa é certa, quanto mais profundamente confuso você fica em sua vida, mais aberta sua mente se torna para novas ideias.",
    "author": "Neil deGrasse Tyson",
    "lang": "pt",
    "tags": [],
    "source": "local"
  },
  {
    "id": "neil-degrass-7380b3fd17",
    "quote": "Saber como pensar torna a pessoa muito mais capaz do que aquele que apenas sabe o que deve pensar.",
    "author": "Neil deGrasse Tyson",
    "lang": "pt",
    "tags": [],
    "source": "local"
  },
  {
    "id": "neil-degrass-6532adb00b",
    "quote": "Curioso que passamos mais tempo parabenizando as pessoas que tiveram sucesso do que incentivando as pessoas que não conseguiram.",
    "author": "Neil deGrasse Tyson",
    "lang": "pt",
    "tags": [],
    "source": "local"
  },
  {
    "id": "roberto-shin-72b916b588",
    "quote": "Tudo o que um sonho precisa para ser realizado é alguém que acredite que ele possa ser realizado.",
    "author": "Roberto Shinyashiki",
    "lang": "pt",
    "tags": [],
    "source": "local"
  },
  {
    "id": "william-shak-121f8f5166",
    "quote": "Nossas dúvidas são traidoras e nos fazem perder o que, com frequência, poderíamos ganhar, por simples medo de arriscar.",
    "author": "William Shakespeare",
    "lang": "pt",
    "tags": [],
    "source": "local"
  },
  {
    "id": "william-shak-c5d1f7370d",
    "quote": "Conservar algo que possa recordar-te seria admitir que eu pudesse esquecer-te.",
    "author": "William Shakespeare",
    "lang": "pt",
    "tags": [],
    "source": "local"
  },
  {
    "id": "charles-chap-bc10938838",
    "quote": "A persistência é o caminho do êxito.",
    "author": "Charles Chaplin",
    "lang": "pt",
    "tags": [],
    "source": "local"
  },
  {
    "id": "tumblr-d55d5fb1af",
    "quote": "Lute. Acredite. Conquiste. Perca. Deseje. Espere. Alcance. Invada. Caia. Seja tudo o quiser ser, mas acima de tudo, seja você sempre.",
    "author": "Tumblr",
    "lang": "pt",
    "tags": [],
    "source": "local"
  },
  {
    "id": "charlie-brow-9537138255",
    "quote": "Eu faço da dificuldade a minha motivação. A volta por cima vem na continuação.",
    "author": "Charlie Brown Jr",
    "lang": "pt",
    "tags": [],
    "source": "local"
  },
  {
    "id": "martin-luthe-a5ff19a9c8",
    "quote": "O que me preocupa não é o grito dos maus. É o silêncio dos bons.",
    "author": "Martin Luther King",
    "lang": "pt",
    "tags": [],
    "source": "local"
  },
  {
    "id": "henry-ford-f9c96f8cf8",
    "quote": "O insucesso é apenas uma oportunidade para recomeçar com mais inteligência.",
    "author": "Henry Ford",
    "lang": "pt",
    "tags": [],
    "source": "local"
  },
  {
    "id": "friedrich-ni-80bdcbadc5",
    "quote": "Só se pode alcançar um grande êxito quando nos mantemos fiéis a nós mesmos.",
    "author": "Friedrich Nietzsche",
    "lang": "pt",
    "tags": [],
    "source": "local"
  },
  {
    "id": "madre-teresa-3b6a493af5",
    "quote": "Por vezes sentimos que aquilo que fazemos não é senão uma gota de água no mar. Mas o mar seria menor se lhe faltasse uma gota.",
    "author": "Madre Teresa de Calcutá",
    "lang": "pt",
    "tags": [],
    "source": "local"
  },
  {
    "id": "mark-twain-94c51c407e",
    "quote": "Coragem é a resistência ao medo, domínio do medo, e não a ausência do medo.",
    "author": "Mark Twain",
    "lang": "pt",
    "tags": [],
    "source": "local"
  },
  {
    "id": "cynthia-kers-084c863d9d",
    "quote": "Acredite em si próprio e chegará um dia em que os outros não terão outra escolha senão acreditar com você.",
    "author": "Cynthia Kersey",
    "lang": "pt",
    "tags": [],
    "source": "local"
  },
  {
    "id": "martin-luthe-d845204279",
    "quote": "A verdadeira medida de um homem não se vê na forma como se comporta em momentos de conforto e conveniência, mas em como se mantém em tempos de controvérsia e desafio.",
    "author": "Martin Luther King",
    "lang": "pt",
    "tags": [],
    "source": "local"
  },
  {
    "id": "martin-luthe-7701b9fbde",
    "quote": "Aprendemos a voar como os pássaros e a nadar como os peixes, mas não aprendemos a conviver como irmãos.",
    "author": "Martin Luther King",
    "lang": "pt",
    "tags": [],
    "source": "local"
  },
  {
    "id": "les-brown-b35336a93d",
    "quote": "Muitos de nós não estamos vivendo nossos sonhos porque estamos vivendo nossos medos.",
    "author": "Les Brown",
    "lang": "pt",
    "tags": [],
    "source": "local"
  },
  {
    "id": "charles-dick-5eb4ca8179",
    "quote": "Somos nós que forjamos as correntes que usamos em nossas vidas.",
    "author": "Charles Dickens",
    "lang": "pt",
    "tags": [],
    "source": "local"
  },
  {
    "id": "walt-disney-08cc28209a",
    "quote": "A melhor maneira de começar alguma coisa é parar de falar e dar o primeiro passo.",
    "author": "Walt Disney",
    "lang": "pt",
    "tags": [],
    "source": "local"
  },
  {
    "id": "amelia-earha-b973a1766b",
    "quote": "A coisa mais difícil é a decisão de agir, o resto é apenas tenacidade.",
    "author": "Amelia Earhart",
    "lang": "pt",
    "tags": [],
    "source": "local"
  },
  {
    "id": "larry-page-13c3c64861",
    "quote": "Vá sempre além do que é esperado.",
    "author": "Larry Page",
    "lang": "pt",
    "tags": [],
    "source": "local"
  },
  {
    "id": "stephen-hawk-429332f74e",
    "quote": "Por mais difícil que a vida pareça ser, sempre há algo que você pode fazer – e fazer bem.",
    "author": "Stephen Hawking",
    "lang": "pt",
    "tags": [],
    "source": "local"
  },
  {
    "id": "stephen-hawk-6964b9cfc3",
    "quote": "Inteligência é a capacidade de se adaptar à mudança.",
    "author": "Stephen Hawking",
    "lang": "pt",
    "tags": [],
    "source": "local"
  },
  {
    "id": "stephen-hawk-f9f61e2dbb",
    "quote": "O paraíso é um conto de fadas para pessoas com medo do escuro.",
    "author": "Stephen Hawking",
    "lang": "pt",
    "tags": [],
    "source": "local"
  },
  {
    "id": "stephen-hawk-a9c5f17e50",
    "quote": "Não importa quanto a vida possa ser ruim, sempre existe algo que você pode fazer, e triunfar. Enquanto há vida, há esperança.",
    "author": "Stephen Hawking",
    "lang": "pt",
    "tags": [],
    "source": "local"
  },
  {
    "id": "stephen-hawk-760a690498",
    "quote": "As grandes conquistas da humanidade foram obtidas conversando, e as grandes falhas pela falta de diálogo.",
    "author": "Stephen Hawking",
    "lang": "pt",
    "tags": [],
    "source": "local"
  },
  {
    "id": "stephen-hawk-66ef1fd295",
    "quote": "Quando alguém reclamar que você cometeu um erro, diga-lhe que pode ser algo bom. Porque sem a imperfeição nem você e nem eu existiríamos.",
    "author": "Stephen Hawking",
    "lang": "pt",
    "tags": [],
    "source": "local"
  },
  {
    "id": "stephen-hawk-90ec3937e2",
    "quote": "A poluição, a ganância e a estupidez são as maiores ameaças ao planeta.",
    "author": "Stephen Hawking",
    "lang": "pt",
    "tags": [],
    "source": "local"
  },
  {
    "id": "stephen-hawk-c9380670e2",
    "quote": "Inteligência é a capacidade de se adaptar a mudanças. A genialidade é antes de tudo a habilidade de aceitar a disciplina.",
    "author": "Stephen Hawking",
    "lang": "pt",
    "tags": [],
    "source": "local"
  },
  {
    "id": "reid-hoffman-5923a62aa2",
    "quote": "Se você não sente vergonha da primeira versão do seu produto, então ele foi lançado depois da hora.",
    "author": "Reid Hoffman",
    "lang": "pt",
    "tags": [],
    "source": "local"
  },
  {
    "id": "johann-wolfg-6d50695b17",
    "quote": "Tudo que você pode fazer, ou sonha que pode, comece. Ousadia tem genialidade, poder e magia.",
    "author": "Johann Wolfgang von Goethe",
    "lang": "pt",
    "tags": [],
    "source": "local"
  },
  {
    "id": "charles-darw-67b06866dc",
    "quote": "Não é o mais forte que sobrevive, nem o mais inteligente. Quem sobrevive é o mais disposto à mudança.",
    "author": "Charles Darwin",
    "lang": "pt",
    "tags": [],
    "source": "local"
  },
  {
    "id": "pablo-picass-b16c04e97b",
    "quote": "Só evite fazer algo hoje se você quiser morrer e deixar assuntos inacabados.",
    "author": "Pablo Picasso",
    "lang": "pt",
    "tags": [],
    "source": "local"
  },
  {
    "id": "winston-chur-c6eeb620b8",
    "quote": "O sucesso não é definitivo, e o fracasso não é fatal: o que importa é a coragem para seguir em frente.",
    "author": "Winston Churchill",
    "lang": "pt",
    "tags": [],
    "source": "local"
  },
  {
    "id": "thomas-jeffe-d2b8be930a",
    "quote": "Quanto mais eu trabalho, maior parece ser a minha sorte.",
    "author": "Thomas Jefferson",
    "lang": "pt",
    "tags": [],
    "source": "local"
  },
  {
    "id": "tina-fey-42260b5d2d",
    "quote": "Não desperdice sua energia tentando mudar opiniões. Faça seu trabalho e não ligue tanto para os outros.",
    "author": "Tina Fey",
    "lang": "pt",
    "tags": [],
    "source": "local"
  },
  {
    "id": "zig-ziglar-98edba733d",
    "quote": "As pessoas costumam dizer que a motivação não dura. Bem, nem o banho. É por isso que recomendamos isso diariamente.",
    "author": "Zig Ziglar",
    "lang": "pt",
    "tags": [],
    "source": "local"
  },
  {
    "id": "jim-ryun-51b0aed898",
    "quote": "Motivação é aquilo que te faz começar. Habito é aquilo que te faz continuar.",
    "author": "Jim Ryun",
    "lang": "pt",
    "tags": [],
    "source": "local"
  },
  {
    "id": "bill-gates-c4253911d8",
    "quote": "Um cliente insatisfeito significa uma nova oportunidade para aprender.",
    "author": "Bill Gates",
    "lang": "pt",
    "tags": [],
    "source": "local"
  },
  {
    "id": "alan-cohen-70817c1779",
    "quote": "Seja feliz com o que você tem, mas fique animado com a chance de ter mais.",
    "author": "Alan Cohen",
    "lang": "pt",
    "tags": [],
    "source": "local"
  },
  {
    "id": "albert-schwe-ba6a0b3715",
    "quote": "O sucesso não é necessário para a felicidade. A felicidade é necessária para o sucesso. Se você ama o que faz, você terá sucesso.",
    "author": "Albert Schweitzer",
    "lang": "pt",
    "tags": [],
    "source": "local"
  },
  {
    "id": "john-wooden-ee84718476",
    "quote": "Não deixe que o que você não pode fazer interfira no que você pode fazer.",
    "author": "John Wooden",
    "lang": "pt",
    "tags": [],
    "source": "local"
  },
  {
    "id": "vince-lombar-2d06ce2be5",
    "quote": "Ganhar não é tudo, mas querer ganhar é.",
    "author": "Vince Lombardi",
    "lang": "pt",
    "tags": [],
    "source": "local"
  },
  {
    "id": "wayne-huizen-785b0be683",
    "quote": "Tem gente que sonha com o sucesso. E tem gente que trabalha todos os dias para conquistá-lo.",
    "author": "Wayne Huizenga",
    "lang": "pt",
    "tags": [],
    "source": "local"
  },
  {
    "id": "joshua-j-mar-004c10d4d3",
    "quote": "Os desafios são o que tornam a vida interessante e superá-los é o que dá sentido à vida.",
    "author": "Joshua J. Marinho",
    "lang": "pt",
    "tags": [],
    "source": "local"
  },
  {
    "id": "henry-ford-012390cd41",
    "quote": "Quando tudo parece estar indo contra você, lembre-se que o avião decola contra o vento, não a favor dele.",
    "author": "Henry Ford",
    "lang": "pt",
    "tags": [],
    "source": "local"
  },
  {
    "id": "roy-t-bennet-7a95603cdd",
    "quote": "Não tenha medo do fracasso. Tenha medo de não tentar.",
    "author": "Roy T. Bennett",
    "lang": "pt",
    "tags": [],
    "source": "local"
  },
  {
    "id": "steve-jobs-bccb31fbbb",
    "quote": "A única maneira de fazer um excelente trabalho é amar o que você faz.",
    "author": "Steve Jobs",
    "lang": "pt",
    "tags": [],
    "source": "local"
  },
  {
    "id": "stevie-wonde-7a34c639d9",
    "quote": "A habilidade pode te levar ao topo. Mas é necessário caráter para se manter lá.",
    "author": "Stevie Wonder",
    "lang": "pt",
    "tags": [],
    "source": "local"
  },
  {
    "id": "winston-chur-d4ed029024",
    "quote": "Ter sucesso significa enfrentar um fracasso atrás de outro sem perder o entusiasmo.",
    "author": "Winston Churchill",
    "lang": "pt",
    "tags": [],
    "source": "local"
  },
  {
    "id": "thomas-ediso-19f5dbec55",
    "quote": "Eu nunca falhei. Eu apenas encontrei 10 mil maneiras que não funcionam.",
    "author": "Thomas Edison",
    "lang": "pt",
    "tags": [],
    "source": "local"
  },
  {
    "id": "robert-colli-f95cbaecd9",
    "quote": "O sucesso é a soma de todos aqueles pequenos esforços diários.",
    "author": "Robert Collier",
    "lang": "pt",
    "tags": [],
    "source": "local"
  },
  {
    "id": "tony-robbins-c71e701216",
    "quote": "Se você faz o que sempre fez, vai ter o que sempre teve.",
    "author": "Tony Robbins",
    "lang": "pt",
    "tags": [],
    "source": "local"
  },
  {
    "id": "robert-f-ken-1046727ecb",
    "quote": "Somente aqueles que ousam falhar muito podem conquistar muito.",
    "author": "Robert F. Kennedy",
    "lang": "pt",
    "tags": [],
    "source": "local"
  },
  {
    "id": "prov-rbio-ja-b97b580d25",
    "quote": "Caia sete vezes. Levante-se oito.",
    "author": "Provérbio japonês",
    "lang": "pt",
    "tags": [],
    "source": "local"
  },
  {
    "id": "john-d-rocke-d21219cb34",
    "quote": "Não tenha medo de desistir do bom para perseguir o ótimo.",
    "author": "John D. Rockefeller",
    "lang": "pt",
    "tags": [],
    "source": "local"
  },
  {
    "id": "eleanor-roos-ec88da1997",
    "quote": "Lembre-se que ninguém pode fazer você se sentir inferior sem o seu consentimento.",
    "author": "Eleanor Roosevelt",
    "lang": "pt",
    "tags": [],
    "source": "local"
  },
  {
    "id": "douglas-ives-ad19ce14ea",
    "quote": "Nunca deixe que suas memórias sejam maiores que os seus sonhos.",
    "author": "Douglas Ivester",
    "lang": "pt",
    "tags": [],
    "source": "local"
  },
  {
    "id": "nicole-sheph-9afee136a0",
    "quote": "Você nunca se arrependerá de ser gentil.",
    "author": "Nicole Shepherd",
    "lang": "pt",
    "tags": [],
    "source": "local"
  },
  {
    "id": "sara-blakely-be04607bca",
    "quote": "Aceite o desconhecido, pois muitas vezes aquilo que você desconhece acaba se tornando o seu maior trunfo. É com ele, afinal, que você fará coisas diferentes.",
    "author": "Sara Blakely",
    "lang": "pt",
    "tags": [],
    "source": "local"
  },
  {
    "id": "tony-hsieh-b61d0a4c22",
    "quote": "Não seja convencido. Sempre existirá alguém melhor do que você.",
    "author": "Tony Hsieh",
    "lang": "pt",
    "tags": [],
    "source": "local"
  },
  {
    "id": "herman-melvi-323e602549",
    "quote": "É melhor falhar na originalidade do que ter sucesso na imitação.",
    "author": "Herman Melville",
    "lang": "pt",
    "tags": [],
    "source": "local"
  },
  {
    "id": "francisco-do-c142e89207",
    "quote": "Embora ninguém possa voltar atrás e fazer um novo começo, qualquer um pode começar agora e fazer um novo fim.",
    "author": "Francisco do Espírito Santo",
    "lang": "pt",
    "tags": [],
    "source": "local"
  },
  {
    "id": "desconhecido-ed9c5e149f",
    "quote": "Por mais que você julgue que todos os dias são iguais, eles não são. Cada novo amanhecer revela uma infinidade de novas oportunidades para serem exploradas!",
    "author": "Desconhecido",
    "lang": "pt",
    "tags": [],
    "source": "local"
  },
  {
    "id": "dalai-lama-91726b40bb",
    "quote": "Só existem dois dias no ano em que nada pode ser feito: um se chama ontem e o outro, amanhã. Portanto, hoje é o dia certo para amar, acreditar, fazer e, principalmente, viver!",
    "author": "Dalai Lama",
    "lang": "pt",
    "tags": [],
    "source": "local"
  },
  {
    "id": "desconhecido-daa0f7ca49",
    "quote": "Mesmo enfrentando muitas batalhas, te agradeço Deus por mais uma semana abençoada!",
    "author": "Desconhecido",
    "lang": "pt",
    "tags": [],
    "source": "local"
  },
  {
    "id": "anton-k-kres-5f0cf61dfc",
    "quote": "Você não pode mudar o que aconteceu na semana passada, mas pode aprender com isso, e escolher a felicidade nesta semana.",
    "author": "Anton K. Kressnig",
    "lang": "pt",
    "tags": [],
    "source": "local"
  },
  {
    "id": "desconhecido-83f38b27f3",
    "quote": "Se você tiver total noção das suas capacidades, nada nem ninguém te impedirá de conquistar coisas que nunca antes havia imaginado!",
    "author": "Desconhecido",
    "lang": "pt",
    "tags": [],
    "source": "local"
  },
  {
    "id": "desconhecido-4b004eef70",
    "quote": "Não começamos do zero. Nossos erros e acertos andam conosco. Eles são a sabedoria que trilha nosso caminho.",
    "author": "Desconhecido",
    "lang": "pt",
    "tags": [],
    "source": "local"
  },
  {
    "id": "a-szent-gyor-a2cbec4ea9",
    "quote": "A descoberta consiste em ver o que todos viram e em pensar no que ninguém pensou.",
    "author": "A. Szent-Gyorgyi",
    "lang": "pt",
    "tags": [],
    "source": "local"
  },
  {
    "id": "sarah-westph-973feb1e9a",
    "quote": "Desconfie do destino e acredite em você. Gaste mais horas realizando que sonhando, fazendo que planejando, vivendo que esperando porque, embora quem quase morre esteja vivo, quem quase vive já morreu.",
    "author": "Sarah Westphal",
    "lang": "pt",
    "tags": [],
    "source": "local"
  },
  {
    "id": "theodore-roo-27ad1a734c",
    "quote": "A justiça não consiste em ser neutro entre o certo e o errado, mas em descobrir o certo e sustentá-lo, onde quer que ele se encontre, contra o errado.",
    "author": "Theodore Roosevelt",
    "lang": "pt",
    "tags": [],
    "source": "local"
  },
  {
    "id": "marqu-s-de-m-4a59f9be5f",
    "quote": "Ocupados em descobrir os defeitos alheios, esquecemo-nos de investigar os próprios.",
    "author": "Marquês de Maricá",
    "lang": "pt",
    "tags": [],
    "source": "local"
  },
  {
    "id": "chico-xavier-1423cd84ee",
    "quote": "Procure descobrir o seu caminho na vida. Ninguém é responsável por nosso destino, a não ser nós mesmos.",
    "author": "Chico Xavier",
    "lang": "pt",
    "tags": [],
    "source": "local"
  },
  {
    "id": "chico-xavier-70fe92ad32",
    "quote": "Ambiente limpo não é o que mais se limpa e sim o que menos se suja.",
    "author": "Chico Xavier",
    "lang": "pt",
    "tags": [],
    "source": "local"
  },
  {
    "id": "chico-xavier-2383547491",
    "quote": "Nem sempre terás o que desejas, mas enquanto estiveres ajudando aos outros encontrarás os recursos de que precisas.",
    "author": "Chico Xavier",
    "lang": "pt",
    "tags": [],
    "source": "local"
  },
  {
    "id": "chico-xavier-27d2b9f350",
    "quote": "O Cristo não pediu muita coisa, não exigiu que as pessoas escalassem o Everest ou fizessem grandes sacrifícios. Ele só pediu que nos amássemos uns aos outros.",
    "author": "Chico Xavier",
    "lang": "pt",
    "tags": [],
    "source": "local"
  },
  {
    "id": "chico-xavier-2cc15b4c99",
    "quote": "Fico triste quando alguém me ofende, mas, com certeza, eu ficaria mais triste se fosse eu o ofensor... Magoar alguém é terrível!",
    "author": "Chico Xavier",
    "lang": "pt",
    "tags": [],
    "source": "local"
  },
  {
    "id": "chico-xavier-6fc9919ac4",
    "quote": "Sonhos não morrem, apenas adormecem na alma da gente.",
    "author": "Chico Xavier",
    "lang": "pt",
    "tags": [],
    "source": "local"
  },
  {
    "id": "chico-xavier-f358fe9cd2",
    "quote": "Cada dia que amanhece assemelha-se a uma página em branco, na qual gravamos os nossos pensamentos, ações e atitudes. Na essência, cada dia é a preparação de nosso próprio amanhã.",
    "author": "Chico Xavier",
    "lang": "pt",
    "tags": [],
    "source": "local"
  },
  {
    "id": "chico-xavier-fada9c0f91",
    "quote": "Deus nos concede, a cada dia, uma página de vida nova no livro do tempo. Aquilo que colocarmos nela, corre por nossa conta.",
    "author": "Chico Xavier",
    "lang": "pt",
    "tags": [],
    "source": "local"
  },
  {
    "id": "chico-xavier-a9180c5214",
    "quote": "Nenhuma atividade no bem é insignificante... As mais altas árvores são oriundas de minúsculas sementes.",
    "author": "Chico Xavier",
    "lang": "pt",
    "tags": [],
    "source": "local"
  },
  {
    "id": "chico-xavier-9b093a05b1",
    "quote": "Lembra-te de que falando ou silenciando, sempre é possível fazer algum bem.",
    "author": "Chico Xavier",
    "lang": "pt",
    "tags": [],
    "source": "local"
  }
]